Metadata-Version: 2.1
Name: dj-taggit-serializer
Version: 0.1.6
Summary: The Django Taggit serializer for tDjango REST Framework
Home-page: https://github.com/adriangzz/dj-taggit-serializer
Author: Paul Oostenrijk, Adrian Gonzalez
Author-email: paul@glemma.nl, adriangonzalezmontemayor@gmail.com
License: BSD
Keywords: dj-taggit-serializer
Platform: UNKNOWN
Classifier: Development Status :: 2 - Pre-Alpha
Classifier: Framework :: Django
Classifier: Intended Audience :: Developers
Classifier: License :: OSI Approved :: BSD License
Classifier: Natural Language :: English
Classifier: Programming Language :: Python :: 2
Classifier: Programming Language :: Python :: 2.6
Classifier: Programming Language :: Python :: 2.7
Classifier: Programming Language :: Python :: 3
Classifier: Programming Language :: Python :: 3.3
License-File: LICENSE
License-File: AUTHORS.rst
